qmetrics/__init__.py
qmetrics/metrics.py
qmetrics-0.0.4.dist-info/LICENSE
qmetrics-0.0.4.dist-info/METADATA
qmetrics-0.0.4.dist-info/WHEEL
qmetrics-0.0.4.dist-info/top_level.txt
qmetrics-0.0.4.dist-info/RECORD
