Metadata-Version: 2.1
Name: qmetrics
Version: 0.0.4
Summary: Quantum Performance Metrics
Home-page: https://github.com/rsathyak/qml_masters_thesis/tree/main/experiments/qmetrics
Author: Rajesh
Author-email: rsathyak@asu.edu
License: Apache 2.0
Project-URL: Bug Tracker, https://github.com/rsathyak/qml_masters_thesis/issues
Project-URL: Documentation, https://github.com/rsathyak/qml_masters_thesis/tree/main/experiments/qmetrics/README.MD
Project-URL: Source Code, https://github.com/rsathyak/qml_masters_thesis/tree/main/experiments/qmetrics
Keywords: quantum performance volume
Platform: UNKNOWN
Classifier: Environment :: Console
Classifier: License :: OSI Approved :: Apache Software License
Classifier: Intended Audience :: Developers
Classifier: Intended Audience :: Science/Research
Classifier: Operating System :: Microsoft :: Windows
Classifier: Operating System :: MacOS
Classifier: Operating System :: POSIX :: Linux
Classifier: Programming Language :: Python :: 3.7
Classifier: Programming Language :: Python :: 3.8
Classifier: Programming Language :: Python :: 3.9
Classifier: Programming Language :: Python :: 3.10
Classifier: Topic :: Scientific/Engineering
Requires-Python: >=3.7
License-File: LICENSE
Requires-Dist: matplotlib
